{
  "data": [
    {
      "id": "691112-rev-limit",
      "title": "Rev Limit",
      "path": "/n64/691112-rev-limit"
    },
    {
      "id": "198475-ridge-racer-64",
      "title": "Ridge Racer 64",
      "path": "/n64/198475-ridge-racer-64"
    },
    {
      "id": "198491-road-rash-64",
      "title": "Road Rash 64",
      "path": "/n64/198491-road-rash-64"
    },
    {
      "id": "198496-roadsters",
      "title": "Roadsters",
      "path": "/n64/198496-roadsters"
    },
    {
      "id": "576602-robopon-64-robot-ponkottsu-64",
      "title": "Robopon 64: Robot Ponkottsu 64",
      "path": "/n64/576602-robopon-64-robot-ponkottsu-64"
    },
    {
      "id": "576602-robopon-64-robot-ponkottsu-64",
      "title": "Robot Ponkottsu 64: Nanatsu no Umi no Caramel",
      "path": "/n64/576602-robopon-64-robot-ponkottsu-64"
    },
    {
      "id": "720852-robotech-crystal-dreams",
      "title": "Robotech: Crystal Dreams",
      "path": "/n64/720852-robotech-crystal-dreams"
    },
    {
      "id": "198501-robotron-64",
      "title": "Robotron 64",
      "path": "/n64/198501-robotron-64"
    },
    {
      "id": "198506-rocket-robot-on-wheels",
      "title": "Rocket: Robot on Wheels",
      "path": "/n64/198506-rocket-robot-on-wheels"
    },
    {
      "id": "913960-mega-man-64",
      "title": "RockMan Dash: Hagane no Boukenshin",
      "path": "/n64/913960-mega-man-64"
    },
    {
      "id": "577028-mia-hamm-64-soccer",
      "title": "RTL WLS 2000",
      "path": "/n64/577028-mia-hamm-64-soccer"
    },
    {
      "id": "915333-rugrats-scavenger-hunt",
      "title": "Rugrats - Die grosse Schatzsuche",
      "path": "/n64/915333-rugrats-scavenger-hunt"
    },
    {
      "id": "913697-rugrats-in-paris-the-movie",
      "title": "Rugrats in Paris: The Movie",
      "path": "/n64/913697-rugrats-in-paris-the-movie"
    },
    {
      "id": "915333-rugrats-scavenger-hunt",
      "title": "Rugrats: Scavenger Hunt",
      "path": "/n64/915333-rugrats-scavenger-hunt"
    },
    {
      "id": "915333-rugrats-scavenger-hunt",
      "title": "Rugrats: Treasure Hunt",
      "path": "/n64/915333-rugrats-scavenger-hunt"
    },
    {
      "id": "198527-rush-2-extreme-racing-usa",
      "title": "Rush 2: Extreme Racing",
      "path": "/n64/198527-rush-2-extreme-racing-usa"
    },
    {
      "id": "198527-rush-2-extreme-racing-usa",
      "title": "Rush 2: Extreme Racing USA",
      "path": "/n64/198527-rush-2-extreme-racing-usa"
    },
    {
      "id": "198533-scars",
      "title": "S.C.A.R.S",
      "path": "/n64/198533-scars"
    },
    {
      "id": "198533-scars",
      "title": "S.C.A.R.S.",
      "path": "/n64/198533-scars"
    },
    {
      "id": "562948-sabans-power-rangers-lightspeed-rescue",
      "title": "Saban's Power Rangers: Lightspeed Rescue",
      "path": "/n64/562948-sabans-power-rangers-lightspeed-rescue"
    },
    {
      "id": "574530-saikyou-habu-shogi",
      "title": "Saikyou Habu Shogi",
      "path": "/n64/574530-saikyou-habu-shogi"
    },
    {
      "id": "198529-san-francisco-rush-2049",
      "title": "San Francisco Rush 2049",
      "path": "/n64/198529-san-francisco-rush-2049"
    },
    {
      "id": "198546-san-francisco-rush-extreme-racing",
      "title": "San Francisco Rush: Extreme Racing",
      "path": "/n64/198546-san-francisco-rush-extreme-racing"
    },
    {
      "id": "374845-scooby-doo-classic-creep-capers",
      "title": "Scooby-Doo! Classic Creep Capers",
      "path": "/n64/374845-scooby-doo-classic-creep-capers"
    },
    {
      "id": "576685-sd-hiryu-no-ken-densetsu",
      "title": "SD Hiryu no Ken Densetsu",
      "path": "/n64/576685-sd-hiryu-no-ken-densetsu"
    },
    {
      "id": "929169-sesame-street-elmos-letter-adventure",
      "title": "Sesame Street: Elmo's Letter Adventure",
      "path": "/n64/929169-sesame-street-elmos-letter-adventure"
    },
    {
      "id": "915907-sesame-street-elmos-number-journey",
      "title": "Sesame Street: Elmo's Number Journey",
      "path": "/n64/915907-sesame-street-elmos-number-journey"
    },
    {
      "id": "198601-shadow-man",
      "title": "Shadow Man",
      "path": "/n64/198601-shadow-man"
    },
    {
      "id": "198608-shadowgate-64-trials-of-the-four-towers",
      "title": "Shadowgate 64: Trials of the Four Towers",
      "path": "/n64/198608-shadowgate-64-trials-of-the-four-towers"
    },
    {
      "id": "672666-shadowgate-rising",
      "title": "Shadowgate Rising",
      "path": "/n64/672666-shadowgate-rising"
    },
    {
      "id": "574540-shin-nippon-pro-wrestling-toukon-road-brave-spirits",
      "title": "Shin Nippon Pro Wrestling: Toukon Road - Brave Spirits",
      "path": "/n64/574540-shin-nippon-pro-wrestling-toukon-road-brave-spirits"
    },
    {
      "id": "574672-shin-nippon-pro-wrestling-toukon-road-2-the-next-generation",
      "title": "Shin Nippon Pro Wrestling: Toukon Road 2 - The Next Generation",
      "path": "/n64/574672-shin-nippon-pro-wrestling-toukon-road-2-the-next-generation"
    },
    {
      "id": "574532-simcity-2000",
      "title": "SimCity 2000",
      "path": "/n64/574532-simcity-2000"
    },
    {
      "id": "366184-sin-and-punishment",
      "title": "Sin & Punishment",
      "path": "/n64/366184-sin-and-punishment"
    },
    {
      "id": "366874-snowboard-kids",
      "title": "Snobow Kids",
      "path": "/n64/366874-snowboard-kids"
    },
    {
      "id": "196757-big-mountain-2000",
      "title": "Snow Speeder",
      "path": "/n64/196757-big-mountain-2000"
    },
    {
      "id": "366874-snowboard-kids",
      "title": "Snowboard Kids",
      "path": "/n64/366874-snowboard-kids"
    },
    {
      "id": "198684-snowboard-kids-2",
      "title": "Snowboard Kids 2",
      "path": "/n64/198684-snowboard-kids-2"
    },
    {
      "id": "196549-aero-fighters-assault",
      "title": "Sonic Wings Assault",
      "path": "/n64/196549-aero-fighters-assault"
    },
    {
      "id": "198710-south-park",
      "title": "South Park",
      "path": "/n64/198710-south-park"
    },
    {
      "id": "198713-south-park-rally",
      "title": "South Park Rally",
      "path": "/n64/198713-south-park-rally"
    },
    {
      "id": "198717-south-park-chefs-luv-shack",
      "title": "South Park: Chef's Luv Shack",
      "path": "/n64/198717-south-park-chefs-luv-shack"
    },
    {
      "id": "197049-dark-rift",
      "title": "Space Dynamites",
      "path": "/n64/197049-dark-rift"
    },
    {
      "id": "198723-space-invaders",
      "title": "Space Invaders",
      "path": "/n64/198723-space-invaders"
    },
    {
      "id": "198727-space-station-silicon-valley",
      "title": "Space Station Silicon Valley",
      "path": "/n64/198727-space-station-silicon-valley"
    },
    {
      "id": "366269-spider-man",
      "title": "Spider-Man",
      "path": "/n64/366269-spider-man"
    },
    {
      "id": "198759-star-fox-64",
      "title": "Star Fox 64",
      "path": "/n64/198759-star-fox-64"
    },
    {
      "id": "562857-star-soldier-vanishing-earth",
      "title": "Star Soldier: Vanishing Earth",
      "path": "/n64/562857-star-soldier-vanishing-earth"
    },
    {
      "id": "197682-jet-force-gemini",
      "title": "Star Twins",
      "path": "/n64/197682-jet-force-gemini"
    },
    {
      "id": "198780-star-wars-episode-i-racer",
      "title": "Star Wars Episode I: Racer",
      "path": "/n64/198780-star-wars-episode-i-racer"
    },
    {
      "id": "914230-star-wars-episode-i-battle-for-naboo",
      "title": "Star Wars: Episode I Battle for Naboo",
      "path": "/n64/914230-star-wars-episode-i-battle-for-naboo"
    },
    {
      "id": "198787-star-wars-rogue-squadron",
      "title": "Star Wars: Rogue Squadron",
      "path": "/n64/198787-star-wars-rogue-squadron"
    },
    {
      "id": "198789-star-wars-shadows-of-the-empire",
      "title": "Star Wars: Shadows of the Empire",
      "path": "/n64/198789-star-wars-shadows-of-the-empire"
    },
    {
      "id": "198787-star-wars-rogue-squadron",
      "title": "Star Wars: Shutsugeki! Rogue Chuutai",
      "path": "/n64/198787-star-wars-rogue-squadron"
    },
    {
      "id": "198789-star-wars-shadows-of-the-empire",
      "title": "Star Wars: Teikoku no Kage",
      "path": "/n64/198789-star-wars-shadows-of-the-empire"
    },
    {
      "id": "198791-starcraft-64",
      "title": "StarCraft 64",
      "path": "/n64/198791-starcraft-64"
    },
    {
      "id": "198799-starshot-space-circus-fever",
      "title": "Starshot: Space Circus Fever",
      "path": "/n64/198799-starshot-space-circus-fever"
    },
    {
      "id": "579310-stunt-racer-64",
      "title": "Stunt Racer 64",
      "path": "/n64/579310-stunt-racer-64"
    },
    {
      "id": "576246-super-b-daman-battle-phoenix-64",
      "title": "Super B-Daman Battle Phoenix 64",
      "path": "/n64/576246-super-b-daman-battle-phoenix-64"
    },
    {
      "id": "576678-super-bowling",
      "title": "Super Bowling",
      "path": "/n64/576678-super-bowling"
    },
    {
      "id": "198848-super-mario-64",
      "title": "Super Mario 64",
      "path": "/n64/198848-super-mario-64"
    },
    {
      "id": "562843-super-robot-spirits",
      "title": "Super Robot Spirits",
      "path": "/n64/562843-super-robot-spirits"
    },
    {
      "id": "576358-super-robot-taisen-64",
      "title": "Super Robot Taisen 64",
      "path": "/n64/576358-super-robot-taisen-64"
    },
    {
      "id": "198854-super-smash-bros",
      "title": "Super Smash Bros.",
      "path": "/n64/198854-super-smash-bros"
    },
    {
      "id": "198859-supercross-2000",
      "title": "Supercross 2000",
      "path": "/n64/198859-supercross-2000"
    },
    {
      "id": "198862-superman-the-new-superman-adventures",
      "title": "Superman",
      "path": "/n64/198862-superman-the-new-superman-adventures"
    },
    {
      "id": "198862-superman-the-new-superman-adventures",
      "title": "Superman: The New Superman Adventures",
      "path": "/n64/198862-superman-the-new-superman-adventures"
    },
    {
      "id": "574497-survivor-day-one",
      "title": "Survivor: Day One",
      "path": "/n64/574497-survivor-day-one"
    },
    {
      "id": "574531-susume-taisen-puzzle-dama-toukon-marutama-chou",
      "title": "Susume! Taisen Puzzle Dama: Toukon! Marutama Chou",
      "path": "/n64/574531-susume-taisen-puzzle-dama-toukon-marutama-chou"
    },
    {
      "id": "917186-sydney-2000",
      "title": "Sydney 2000",
      "path": "/n64/917186-sydney-2000"
    },
    {
      "id": "570144-taz-express",
      "title": "Taz Express",
      "path": "/n64/570144-taz-express"
    },
    {
      "id": "577028-mia-hamm-64-soccer",
      "title": "Telefoot Soccer 2000",
      "path": "/n64/577028-mia-hamm-64-soccer"
    },
    {
      "id": "575365-tetris-64",
      "title": "Tetris 64",
      "path": "/n64/575365-tetris-64"
    },
    {
      "id": "198946-tetrisphere",
      "title": "Tetrisphere",
      "path": "/n64/198946-tetrisphere"
    },
    {
      "id": "576969-tiggers-honey-hunt",
      "title": "Tigger's Honey Hunt",
      "path": "/n64/576969-tiggers-honey-hunt"
    },
    {
      "id": "437520-tom-and-jerry-in-fists-of-furry",
      "title": "Tom and Jerry in Fists of Furry",
      "path": "/n64/437520-tom-and-jerry-in-fists-of-furry"
    },
    {
      "id": "198400-tom-clancys-rainbow-six",
      "title": "Tom Clancy's Rainbow Six",
      "path": "/n64/198400-tom-clancys-rainbow-six"
    },
    {
      "id": "295686-tommy-thunder",
      "title": "Tommy Thunder",
      "path": "/n64/295686-tommy-thunder"
    },
    {
      "id": "199055-tonic-trouble",
      "title": "Tonic Trouble",
      "path": "/n64/199055-tonic-trouble"
    },
    {
      "id": "199059-tony-hawks-pro-skater",
      "title": "Tony Hawk's Pro Skater",
      "path": "/n64/199059-tony-hawks-pro-skater"
    },
    {
      "id": "470189-tony-hawks-pro-skater-2",
      "title": "Tony Hawk's Pro Skater 2",
      "path": "/n64/470189-tony-hawks-pro-skater-2"
    },
    {
      "id": "914527-tony-hawks-pro-skater-3",
      "title": "Tony Hawk's Pro Skater 3",
      "path": "/n64/914527-tony-hawks-pro-skater-3"
    },
    {
      "id": "199059-tony-hawks-pro-skater",
      "title": "Tony Hawk's Skateboarding",
      "path": "/n64/199059-tony-hawks-pro-skater"
    },
    {
      "id": "127448-toon-panic",
      "title": "Toon Panic",
      "path": "/n64/127448-toon-panic"
    },
    {
      "id": "199066-top-gear-hyper-bike",
      "title": "Top Gear Hyper Bike",
      "path": "/n64/199066-top-gear-hyper-bike"
    },
    {
      "id": "199066-top-gear-hyper-bike",
      "title": "Top Gear Hyper-Bike",
      "path": "/n64/199066-top-gear-hyper-bike"
    },
    {
      "id": "199067-top-gear-overdrive",
      "title": "Top Gear Overdrive",
      "path": "/n64/199067-top-gear-overdrive"
    },
    {
      "id": "199069-top-gear-rally",
      "title": "Top Gear Rally",
      "path": "/n64/199069-top-gear-rally"
    },
    {
      "id": "199070-top-gear-rally-2",
      "title": "Top Gear Rally 2",
      "path": "/n64/199070-top-gear-rally-2"
    },
    {
      "id": "212718-top-gun-64",
      "title": "Top Gun 64",
      "path": "/n64/212718-top-gun-64"
    },
    {
      "id": "576667-transformers-beast-wars-transmetals",
      "title": "Transformers: Beast Wars Metals 64",
      "path": "/n64/576667-transformers-beast-wars-transmetals"
    },
    {
      "id": "576667-transformers-beast-wars-transmetals",
      "title": "Transformers: Beast Wars Transmetals",
      "path": "/n64/576667-transformers-beast-wars-transmetals"
    },
    {
      "id": "199111-triple-play-2000",
      "title": "Triple Play 2000",
      "path": "/n64/199111-triple-play-2000"
    },
    {
      "id": "366184-sin-and-punishment",
      "title": "Tsumi to Batsu: Hoshi no Keishousha",
      "path": "/n64/366184-sin-and-punishment"
    },
    {
      "id": "199127-turok-2-seeds-of-evil",
      "title": "Turok 2: Seeds of Evil",
      "path": "/n64/199127-turok-2-seeds-of-evil"
    },
    {
      "id": "199128-turok-3-shadow-of-oblivion",
      "title": "Turok 3: Shadow of Oblivion",
      "path": "/n64/199128-turok-3-shadow-of-oblivion"
    },
    {
      "id": "199130-turok-dinosaur-hunter",
      "title": "Turok: Dinosaur Hunter",
      "path": "/n64/199130-turok-dinosaur-hunter"
    },
    {
      "id": "199132-turok-rage-wars",
      "title": "Turok: Legenden des Verlorenen Landes",
      "path": "/n64/199132-turok-rage-wars"
    },
    {
      "id": "199132-turok-rage-wars",
      "title": "Turok: Rage Wars",
      "path": "/n64/199132-turok-rage-wars"
    },
    {
      "id": "199134-twisted-edge-extreme-snowboarding",
      "title": "Twisted Edge Extreme Snowboarding",
      "path": "/n64/199134-twisted-edge-extreme-snowboarding"
    }
  ]
}